anycastd-0.1.12.dist-info/METADATA
anycastd-0.1.12.dist-info/WHEEL
anycastd-0.1.12.dist-info/entry_points.txt
anycastd-0.1.12.dist-info/licenses/LICENSE
anycastd/__init__.py
anycastd/__main__.py
anycastd/_cli/__init__.py
anycastd/_cli/main.py
anycastd/_cli/output.py
anycastd/_configuration/__init__.py
anycastd/_configuration/conversion.py
anycastd/_configuration/exceptions.py
anycastd/_configuration/healthcheck.py
anycastd/_configuration/main.py
anycastd/_configuration/prefix.py
anycastd/_configuration/service.py
anycastd/_configuration/sub.py
anycastd/_executor.py
anycastd/core/__init__.py
anycastd/core/_exit.py
anycastd/core/_run.py
anycastd/core/_service.py
anycastd/healthcheck/__init__.py
anycastd/healthcheck/_cabourotte/__init__.py
anycastd/healthcheck/_cabourotte/exceptions.py
anycastd/healthcheck/_cabourotte/main.py
anycastd/healthcheck/_cabourotte/result.py
anycastd/healthcheck/_common.py
anycastd/healthcheck/_main.py
anycastd/prefix/__init__.py
anycastd/prefix/_frrouting/__init__.py
anycastd/prefix/_frrouting/exceptions.py
anycastd/prefix/_frrouting/main.py
anycastd/prefix/_main.py
anycastd/py.typed
anycastd-0.1.12.dist-info/RECORD
