Metadata-Version: 2.1
Name: anycastd
Version: 0.1.12
Summary: A daemon to manage anycasted services based on status checks.
Keywords: anycast,bgp,dns,frrouting,monitoring,networking,infrastructure,routing,healthcheck
Author-Email: Marvin Vogt <m@rvinvogt.com>
License: Apache-2.0
Classifier: Development Status :: 4 - Beta
Classifier: Intended Audience :: Developers
Classifier: Operating System :: Unix
Classifier: Operating System :: POSIX
Classifier: Programming Language :: Python
Classifier: Programming Language :: Python :: 3.11
Classifier: Programming Language :: Python :: 3.12
Classifier: Topic :: Internet
Classifier: Topic :: Internet :: Name Service (DNS)
Classifier: Topic :: System :: Clustering
Classifier: Topic :: System :: Monitoring
Classifier: Topic :: System :: Networking
Classifier: Intended Audience :: Information Technology
Classifier: Intended Audience :: Telecommunications Industry
Classifier: Intended Audience :: System Administrators
Classifier: Typing :: Typed
Project-URL: Repository, https://github.com/gecio/anycastd
Project-URL: Issues, https://github.com/gecio/anycastd/issues
Requires-Python: >=3.11
Requires-Dist: pydantic>=2.5.2
Requires-Dist: httpx>=0.25.0
Requires-Dist: typer[all]>=0.9.0
Requires-Dist: structlog>=24.1.0
Requires-Dist: rich>=13.7.0
Requires-Dist: orjson>=3.9.13
